Workbook

Sheet Value per user
A1: PayWatch — Value Created per User
A2: Figures marked ENGINE were computed by PayWatch's own deterministic engines over 15 representative Indian profiles (the demo personas). They are OPPORTUNITIES IDENTIFIED, not yet realised outcomes — realised value is what the validation phase will measure.
A3: Yellow = your assumption to edit. Blue = input. Black = formula.
A5: 1 · WHAT THE ENGINE IDENTIFIES (per user)
A6: Tax-saving opportunities identified / yr (₹) | B6: 100000 | D6: ENGINE avg was ₹1.28L; using a conservative ₹1.0L
A7: Projected 10-yr wealth uplift from the plan (₹) | B7: 4000000 | D7: ENGINE avg 10-yr uplift was ₹65.8L; conservative ₹40L (nominal, illustrative)
A8: Under-insurance (protection gap) surfaced / user (₹) | B8: 2000000 | D8: ENGINE avg ₹3.8Cr (skewed by HNI); using ₹20L — informational, not 'saved'
A9: Hours/yr saved vs manual + advisor coordination | B9: 12 | D9: ASSUMPTION — validate with users (Vighnesh)
A10: Value of user's time (₹/hour) | B10: 300 | D10: ASSUMPTION
A12: 2 · REALISED VALUE (what users actually capture)
A13: Realised capture rate (% of identified value acted on) | B13: 0.25 | D13: KEY ASSUMPTION — users act on a fraction; validate
A14: Realised tax value / user / yr (₹) | B14: =B6*B13 -> 25000
A15: Realised time value / user / yr (₹) | B15: =B9*B10 -> 3600
A16: Realised direct value / user / yr (₹) | B16: =B14+B15 -> 28600 | D16: Tax + time (the defensible, near-term number)
A17: + Projected long-term wealth uplift / user (₹) | B17: =B7*B13 -> 1000000 | D17: 10-yr, illustrative — the 'why it matters' number
A19: 3 · AGGREGATE VALUE CREATED (at scale)
A20: Users | B20: Realised value/yr created | C20: Cumulative wealth uplift
A21: 1000 | B21: =A21*$B$16 -> 28600000 | C21: =A21*$B$17 -> 1000000000
A22: 10000 | B22: =A22*$B$16 -> 286000000 | C22: =A22*$B$17 -> 10000000000
A23: 100000 | B23: =A23*$B$16 -> 2860000000 | C23: =A23*$B$17 -> 100000000000
A24: 1000000 | B24: =A24*$B$16 -> 28600000000 | C24: =A24*$B$17 -> 1000000000000
A26: Headline for investors: at 100k users PayWatch identifies ~₹1L+/user/yr in tax alone; even at a 25% realised capture it creates real, measurable rupee value — and validation will report the ACTUAL capture rate.

Sheet Cost curve & breakeven
A1: Cost per User & Breakeven
A2: How per-user cost falls as fixed costs spread over more users, and the user count where PayWatch turns profitable.
A4: ASSUMPTIONS
A5: ARPU per PAYING user / mo (₹) | B5: 354 | C5: subscription + distribution blend
A6: Free → paid conversion | B6: 0.05
A7: Blended revenue per ACTIVE user / mo (₹) | B7: =B5*B6 -> 17.7 | C7: ARPU times conversion
A8: Variable cost per active user / mo (₹) | B8: 15 | C8: AI API + infra + support + PG
A9: Fixed cost / mo (₹) | B9: 150000 | C9: team + infra base + tools
A10: Contribution / active user / mo (₹) | B10: =B7-B8 -> 2.7 | C10: revenue − variable cost
A11: BREAKEVEN — active users needed | B11: =IF(B10>0,B9/B10,0) -> 55555.556 | C11: fixed ÷ contribution/user
A13: COST PER USER AS YOU SCALE
A14: Active users | B14: Cost / user / mo | C14: Revenue / user | D14: Profit / user | E14: Monthly profit
A15: 100 | B15: =$B$9/A15+$B$8 -> 1515 | C15: =$B$7 -> 17.7 | D15: =C15-B15 -> -1497.3 | E15: =A15*(C15-$B$8)-$B$9 -> -149730
A16: 500 | B16: =$B$9/A16+$B$8 -> 315 | C16: =$B$7 -> 17.7 | D16: =C16-B16 -> -297.3 | E16: =A16*(C16-$B$8)-$B$9 -> -148650
A17: 1000 | B17: =$B$9/A17+$B$8 -> 165 | C17: =$B$7 -> 17.7 | D17: =C17-B17 -> -147.3 | E17: =A17*(C17-$B$8)-$B$9 -> -147300
A18: 5000 | B18: =$B$9/A18+$B$8 -> 45 | C18: =$B$7 -> 17.7 | D18: =C18-B18 -> -27.3 | E18: =A18*(C18-$B$8)-$B$9 -> -136500
A19: 10000 | B19: =$B$9/A19+$B$8 -> 30 | C19: =$B$7 -> 17.7 | D19: =C19-B19 -> -12.3 | E19: =A19*(C19-$B$8)-$B$9 -> -123000
A20: 50000 | B20: =$B$9/A20+$B$8 -> 18 | C20: =$B$7 -> 17.7 | D20: =C20-B20 -> -0.3 | E20: =A20*(C20-$B$8)-$B$9 -> -15000
A21: 100000 | B21: =$B$9/A21+$B$8 -> 16.5 | C21: =$B$7 -> 17.7 | D21: =C21-B21 -> 1.2 | E21: =A21*(C21-$B$8)-$B$9 -> 120000
A22: 500000 | B22: =$B$9/A22+$B$8 -> 15.3 | C22: =$B$7 -> 17.7 | D22: =C22-B22 -> 2.4 | E22: =A22*(C22-$B$8)-$B$9 -> 1200000
A24: Read it: cost/user falls fast as fixed cost spreads; profit/user turns positive once you pass the breakeven user count above. This is the classic software scale curve.

Sheet Scale plan
A1: Scalability Plan — path to profit
A2: Milestone view. Edit the yellow user targets per milestone; the rest computes. All monthly figures.
A4: Metric | B4: Launch | C4: Month 6 | D4: Month 12 | E4: Month 18 | F4: Month 24
A5: Total active users | B5: 500 | C5: 10000 | D5: 60000 | E5: 200000 | F5: 500000
A6: Paying users | B6: =B5*'Cost curve & breakeven'!$B$6 -> 25 | C6: =C5*'Cost curve & breakeven'!$B$6 -> 500 | D6: =D5*'Cost curve & breakeven'!$B$6 -> 3000 | E6: =E5*'Cost curve & breakeven'!$B$6 -> 10000 | F6: =F5*'Cost curve & breakeven'!$B$6 -> 25000
A7: MRR (₹) | B7: =B6*'Cost curve & breakeven'!$B$5 -> 8850 | C7: =C6*'Cost curve & breakeven'!$B$5 -> 177000 | D7: =D6*'Cost curve & breakeven'!$B$5 -> 1062000 | E7: =E6*'Cost curve & breakeven'!$B$5 -> 3540000 | F7: =F6*'Cost curve & breakeven'!$B$5 -> 8850000
A8: Monthly cost (₹) | B8: ='Cost curve & breakeven'!$B$9+B5*'Cost curve & breakeven'!$B$8 -> 157500 | C8: ='Cost curve & breakeven'!$B$9+C5*'Cost curve & breakeven'!$B$8 -> 300000 | D8: ='Cost curve & breakeven'!$B$9+D5*'Cost curve & breakeven'!$B$8 -> 1050000 | E8: ='Cost curve & breakeven'!$B$9+E5*'Cost curve & breakeven'!$B$8 -> 3150000 | F8: ='Cost curve & breakeven'!$B$9+F5*'Cost curve & breakeven'!$B$8 -> 7650000 | G8: fixed + variable×users (fixed may step up in reality)
A9: Monthly profit (₹) | B9: =B7-B8 -> -148650 | C9: =C7-C8 -> -123000 | D9: =D7-D8 -> 12000 | E9: =E7-E8 -> 390000 | F9: =F7-F8 -> 1200000
A10: Value created/yr for users (₹) | B10: =B5*'Value per user'!$B$16 -> 14300000 | C10: =C5*'Value per user'!$B$16 -> 286000000 | D10: =D5*'Value per user'!$B$16 -> 1716000000 | E10: =E5*'Value per user'!$B$16 -> 5720000000 | F10: =F5*'Value per user'!$B$16 -> 14300000000 | G10: realised direct value × users
A12: Note: the fixed cost is held flat here for clarity; in reality it steps up as you hire — model that when you have real numbers. Breakeven is where Monthly profit turns positive.
A13: All numbers are a planning model on stated assumptions, not a forecast. Replace the yellow cells with real figures as validation produces them.
